cdp_gh_utils/__init__.py
cdp_gh_utils/actions.py
cdp_gh_utils/py.typed
cdp_gh_utils/bin/__init__.py
cdp_gh_utils/bin/backfill_cdp_instance.py
cdp_gh_utils/tests/conftest.py
cdp_gh_utils/tests/test_actions.py
docs/conf.py
docs/contributing.rst
docs/index.rst
docs/installation.rst
cdp_gh_utils-0.2.0.dist-info/LICENSE
cdp_gh_utils-0.2.0.dist-info/METADATA
cdp_gh_utils-0.2.0.dist-info/WHEEL
cdp_gh_utils-0.2.0.dist-info/entry_points.txt
cdp_gh_utils-0.2.0.dist-info/top_level.txt
cdp_gh_utils-0.2.0.dist-info/RECORD
